[
    {
        "hash": "36cf45ef3ba71e44a8be06ee81cb31aa02cb0010",
        "symbol": [
            "ossl_sm2_plaintext_size"
        ]
    },
    {
        "hash": "ed576acdf591d4164905ab98e89ca5a3b99d90ab",
        "symbol": [
            "ossl_sm2_plaintext_size"
        ]
    },
    {
        "hash": "32ab57cbb4877ce7e6b4eb3f9b3cfbb0ff7cd10b",
        "symbol": [
            "ossl_sm2_plaintext_size"
        ]
    },
    {
        "hash": "9311d0c471ca2eaa259e8c1bbbeb7c46394c7ba2",
        "symbol": [
            "ossl_sm2_plaintext_size"
        ]
    },
    {
        "hash": "2167239abaec5fa44072fa1194505af0b3fced89",
        "symbol": [
            "ossl_sm2_plaintext_size"
        ]
    },
    {
        "hash": "245be5304d7c8e4a4345c971791cbf03cb5ca603",
        "symbol": [
            "ossl_sm2_plaintext_size"
        ]
    },
    {
        "hash": "e14d6cf691c9d8ad49df280b580b6836a67c6a19",
        "symbol": [
            "ossl_sm2_plaintext_size"
        ]
    },
    {
        "hash": "4e6647506331fc3b3ef5b23e5dbe188279ddd575",
        "symbol": [
            "ossl_sm2_plaintext_size"
        ]
    }
]